webwithpy/__init__.py
webwithpy/app.py
webwithpy/commands.py
webwithpy/exeptions/HttpExceptions.py
webwithpy/exeptions/RouteExceptions.py
webwithpy/exeptions/__init__.py
webwithpy/helper/__init__.py
webwithpy/helper/async_handler.py
webwithpy/html/__init__.py
webwithpy/html/data/__init__.py
webwithpy/html/data/ast.py
webwithpy/html/data/token.py
webwithpy/html/forms.py
webwithpy/html/helpers/__init__.py
webwithpy/html/helpers/str_helper.py
webwithpy/html/html_exception/__init__.py
webwithpy/html/html_exception/exceptions.py
webwithpy/html/lexer.py
webwithpy/html/parser.py
webwithpy/html/pyhtml.py
webwithpy/html/renderer.py
webwithpy/http/__init__.py
webwithpy/http/cookies.py
webwithpy/http/handler.py
webwithpy/http/redirect.py
webwithpy/http/request.py
webwithpy/http/response.py
webwithpy/http/urls.py
webwithpy/orm/__init__.py
webwithpy/orm/auth.py
webwithpy/orm/core.py
webwithpy/orm/dialect/__init__.py
webwithpy/orm/dialect/base.py
webwithpy/orm/dialect/mysql.py
webwithpy/orm/dialect/sqlite.py
webwithpy/orm/drivers/__init__.py
webwithpy/orm/drivers/driver.py
webwithpy/orm/drivers/mysql.py
webwithpy/orm/drivers/sqlite.py
webwithpy/orm/helpers/__init__.py
webwithpy/orm/helpers/settings.py
webwithpy/orm/objects/__init__.py
webwithpy/orm/objects/objects.py
webwithpy/orm/objects/query.py
webwithpy/persistence.py
webwithpy/routing/__init__.py
webwithpy/routing/methods.py
webwithpy/routing/router.py
webwithpy/static/form.css
webwithpy/static/improved_reg_form.css
webwithpy/tests/__init__.py
webwithpy/tests/case.py
webwithpy/tests/helper.py
webwithpy/webwithpy.py
webwithpy-0.7.5.3.dist-info/LICENSE
webwithpy-0.7.5.3.dist-info/METADATA
webwithpy-0.7.5.3.dist-info/WHEEL
webwithpy-0.7.5.3.dist-info/entry_points.txt
webwithpy-0.7.5.3.dist-info/RECORD
