Metadata-Version: 2.1
Name: webwithpy
Version: 0.7.5.3
Summary: 
Author: Sven Keimpema
Requires-Python: >=3.10,<4.0
Classifier: Programming Language :: Python :: 3
Classifier: Programming Language :: Python :: 3.10
Classifier: Programming Language :: Python :: 3.11
Classifier: Programming Language :: Python :: 3.12
Requires-Dist: asyncio (>=3.4.3,<4.0.0)
Requires-Dist: bcrypt (>=3.2.0,<4.0.0)
Requires-Dist: click (>=8.1.7,<9.0.0)
Requires-Dist: cython (>=3.0.5,<4.0.0)
Requires-Dist: mysql-connector-python (>=8.3.0,<9.0.0)
Requires-Dist: pyjwt (>=2.8.0,<3.0.0)
Requires-Dist: requests-toolbelt (>=1.0.0,<2.0.0)
Requires-Dist: setuptools (>=69.0.2,<70.0.0)
